tabular_reader/__init__.py
tabular_reader/reader.py
tabular_reader-0.1.2.dist-info/METADATA
tabular_reader-0.1.2.dist-info/WHEEL
tabular_reader-0.1.2.dist-info/licenses/LICENSE
tabular_reader-0.1.2.dist-info/RECORD
