Metadata-Version: 2.4
Name: tabular-reader
Version: 0.1.2
Summary: Read XLSX, XLS and CSV files with a uniform interface Read XLSX, XLS and CSV files with a uniform interface
License: MIT
License-File: LICENSE
Keywords: spreadsheet,csv,xlsx,xls,reader
Author: arkhan
Author-email: arkhan@riseup.net
Requires-Python: >=3.6,<4.0
Classifier: Development Status :: 3 - Alpha
Classifier: Intended Audience :: Developers
Classifier: License :: OSI Approved :: MIT License
Classifier: Programming Language :: Python :: 3
Classifier: Programming Language :: Python :: 3.6
Classifier: Programming Language :: Python :: 3.7
Classifier: Programming Language :: Python :: 3.8
Classifier: Programming Language :: Python :: 3.9
Classifier: Programming Language :: Python :: 3.10
Classifier: Programming Language :: Python :: 3.11
Classifier: Programming Language :: Python :: 3.12
Classifier: Programming Language :: Python :: 3.13
Classifier: Programming Language :: Python :: 3.14
Requires-Dist: openpyxl (>=3.0,<3.1)
Requires-Dist: xlrd (>=2.0,<3.0)
Project-URL: Repository, https://github.com/arkhan/tabular-reader
